[
  {
    "Numer": 1,
    "Grawitacja": 2,
    "Bryla sztywna": 1.125,
    "Kosmologia": 0,
    "Plusy": 1    
  },
  {
    "Numer": 3,
    "Grawitacja": 2.5,
    "Bryla sztywna": 1,
    "Kosmologia": 0,
    "Plusy": 10     
  },
  {
    "Numer": 4,
    "Grawitacja": 1.75,
    "Bryla sztywna": 1.5,
    "Kosmologia": 0,
    "Plusy": 1     
  },
  {
    "Numer": 5,
    "Grawitacja": 2,
    "Bryla sztywna": 1,
    "Kosmologia": 0,
    "Plusy": 7     
  },
  {
    "Numer": 6,
    "Grawitacja": 3.25,
    "Bryla sztywna": 3.5,
    "Kosmologia": 0,
    "Plusy": 9     
  },
  {
    "Numer": 7,
    "Grawitacja": 1.75,
    "Bryla sztywna": 3.25,
    "Kosmologia": 0,
    "Plusy": 6     
  },
  {
    "Numer": 8,
    "Grawitacja": 2.5,
    "Bryla sztywna": 1.5,
    "Kosmologia": 0,
    "Plusy": 3     
  },
  {
    "Numer": 9,
    "Grawitacja": 2.25,
    "Bryla sztywna": 4.25,
    "Kosmologia": 0,
    "Plusy": 3     
  },
  {
    "Numer": 10,
    "Grawitacja": 2.75,
    "Bryla sztywna": 3.75,
    "Kosmologia": 0,
    "Plusy": 2     
  },
  {
    "Numer": 11,
    "Grawitacja": 2.75,
    "Bryla sztywna": 1.5,
    "Kosmologia": 0,
    "Plusy": 3     
  },
  {
    "Numer": 12,
    "Grawitacja": 2,
    "Bryla sztywna": 0,
    "Kosmologia": 0,
    "Plusy": 1     
  },
  {
    "Numer": 13,
    "Grawitacja": 1.5,
    "Bryla sztywna": 1.5,
    "Kosmologia": 0,
    "Plusy": 0     
  },
  {
    "Numer": 15,
    "Grawitacja": 1.25,
    "Bryla sztywna": 2.25,
    "Kosmologia": 0,
    "Plusy": 0     
  },
  {
    "Numer": 16,
    "Grawitacja": 4.5,
    "Bryla sztywna": 0,
    "Kosmologia": 0,
    "Plusy": 3     
  },
  {
    "Numer": 17,
    "Grawitacja": 2,
    "Bryla sztywna": 4.25,
    "Kosmologia": 0,
    "Plusy": 8     
  },
  {
    "Numer": 18,
    "Grawitacja": 0,
    "Bryla sztywna": 0,
    "Kosmologia": 0,
    "Plusy": 0     
  },
  {
    "Numer": 19,
    "Grawitacja": 2.75,
    "Bryla sztywna": 1,
    "Kosmologia": 0,
    "Plusy": 0     
  },
  {
    "Numer": 20,
    "Grawitacja": 2.75,
    "Bryla sztywna": 1.5,
    "Kosmologia": 0,
    "Plusy": 11     
  },
  {
    "Numer": 21,
    "Grawitacja": 5,
    "Bryla sztywna": 4,
    "Kosmologia": 0,
    "Plusy": 20     
  },
  {
    "Numer": 22,
    "Grawitacja": 2,
    "Bryla sztywna": 1.5,
    "Kosmologia": 0,
    "Plusy": 0     
  },
  {
    "Numer": 23,
    "Grawitacja": 4.75,
    "Bryla sztywna": 4,
    "Kosmologia": 0,
    "Plusy": 3     
  },
  {
    "Numer": 24,
    "Grawitacja": 0,
    "Bryla sztywna": 1,
    "Kosmologia": 0,
    "Plusy": 0     
  },
  {
    "Numer": 25,
    "Grawitacja": 2.25,
    "Bryla sztywna": 0,
    "Kosmologia": 0,
    "Plusy": 0     
  },
  {
    "Numer": 26,
    "Grawitacja": 4,
    "Bryla sztywna": 1.5,
    "Kosmologia": 0,
    "Plusy": 0     
  },
  {
    "Numer": 27,
    "Grawitacja": 2.25,
    "Bryla sztywna": 2,
    "Kosmologia": 0,
    "Plusy": 0     
  },
  {
    "Numer": 28,
    "Grawitacja": 3.5,
    "Bryla sztywna": 2,
    "Kosmologia": 0,
    "Plusy": 4     
  },
  {
    "Numer": 29,
    "Grawitacja": 5.25,
    "Bryla sztywna": 4,
    "Kosmologia": 0,
    "Plusy": 12     
  },
  {
    "Numer": 30,
    "Grawitacja": 3,
    "Bryla sztywna": 0.5,
    "Kosmologia": 0,
    "Plusy": 0     
  },
  {
    "Numer": 31,
    "Grawitacja": 2.25,
    "Bryla sztywna": 2,
    "Kosmologia": 0,
    "Plusy": 0     
  },
  {
    "Numer": 32,
    "Grawitacja": 2,
    "Bryla sztywna": 0.5,
    "Kosmologia": 0,
    "Plusy": 3     
  },
  {
    "Numer": 33,
    "Grawitacja": 3.75,
    "Bryla sztywna": 1.5,
    "Kosmologia": 0,
    "Plusy": 0     
  },
  {
    "Numer": 34,
    "Grawitacja": 2.25,
    "Bryla sztywna": 1.5,
    "Kosmologia": 0,
    "Plusy": 3     
  },
  {
    "Numer": 35,
    "Grawitacja": 2.5,
    "Bryla sztywna": 1,
    "Kosmologia": 0,
    "Plusy": 6     
  }
]
